django_pypayzen/__init__.py
django_pypayzen/admin.py
django_pypayzen/app_settings.py
django_pypayzen/apps.py
django_pypayzen/constants.py
django_pypayzen/forms.py
django_pypayzen/models.py
django_pypayzen/signals.py
django_pypayzen/tools.py
django_pypayzen/urls.py
django_pypayzen/views.py
django_pypayzen/migrations/0001_initial.py
django_pypayzen/migrations/0002_auto_20141024_0822.py
django_pypayzen/migrations/0003_auto_20141027_1647.py
django_pypayzen/migrations/0004_auto_20141221_2140.py
django_pypayzen/migrations/__init__.py
django_pypayzen/templates/django_pypayzen/auto_submit_form.html
django_pypayzen/templates/django_pypayzen/form.html
django_pypayzen/templatetags/__init__.py
django_pypayzen/templatetags/payzen_extras.py
django_pypayzen/tests/__init__.py
django_pypayzen/tests/data.py
django_pypayzen/tests/payzen_init/__init__.py
django_pypayzen/tests/payzen_init/tests.py
django_pypayzen/tests/payzen_response/__init__.py
django_pypayzen/tests/payzen_response/tests.py
django_pypayzen/tests/request_data/__init__.py
django_pypayzen/tests/request_data/tests.py
django_pypayzen-0.4.dist-info/DESCRIPTION.rst
django_pypayzen-0.4.dist-info/METADATA
django_pypayzen-0.4.dist-info/RECORD
django_pypayzen-0.4.dist-info/WHEEL
django_pypayzen-0.4.dist-info/metadata.json
django_pypayzen-0.4.dist-info/top_level.txt
tests/__init__.py
tests/test_cmd.py
tests/urls.py
