Metadata-Version: 2.0
Name: django-pypayzen
Version: 0.4
Summary: Django app to manage payments with Payzen ETP
Home-page: https://github.com/samambaman/django-pypayzen
Author: Felipe Ferreira
Author-email: felipe.gomes.ferreira@gmail.com
License: MIT
Platform: UNKNOWN
Classifier: Development Status :: 3 - Alpha
Classifier: Environment :: Web Environment
Classifier: Intended Audience :: Developers
Classifier: Operating System :: OS Independent
Classifier: Programming Language :: Python :: 2
Classifier: Programming Language :: Python :: 2.6
Classifier: Programming Language :: Python :: 2.7
Classifier: Programming Language :: Python :: 3
Classifier: Programming Language :: Python :: 3.2
Classifier: Programming Language :: Python :: 3.3
Classifier: Programming Language :: Python :: 3.4
Classifier: Framework :: Django
Classifier: Topic :: Software Development
Requires-Dist: Django
